DnsCryptProxyPiTool/ClickHelperClasses.py
DnsCryptProxyPiTool/Command.py
DnsCryptProxyPiTool/DefaultConfig.py
DnsCryptProxyPiTool/__init__.py
DnsCryptProxyPiTool/FabricService/FabricCommand.py
DnsCryptProxyPiTool/FabricService/FabricExecute.py
DnsCryptProxyPiTool/FabricService/StringContainer.py
DnsCryptProxyPiTool/FabricService/__init__.py
DnsCryptProxyPiTool-0.19.dist-info/DESCRIPTION.rst
DnsCryptProxyPiTool-0.19.dist-info/METADATA
DnsCryptProxyPiTool-0.19.dist-info/RECORD
DnsCryptProxyPiTool-0.19.dist-info/WHEEL
DnsCryptProxyPiTool-0.19.dist-info/entry_points.txt
DnsCryptProxyPiTool-0.19.dist-info/metadata.json
DnsCryptProxyPiTool-0.19.dist-info/top_level.txt
