Metadata-Version: 2.0
Name: DnsCryptProxyPiTool
Version: 0.19
Summary: DnsCrypt Proxy 2 Setup for PiHole Raspberry Pi 3
Home-page: https://github.com/jmcgrath207/DnsCryptProxyPiTool
Author: John McGrath
Author-email: john.mcgrath207@gmail.com
License: MIT License
Platform: UNKNOWN
Classifier: Development Status :: 4 - Beta
Classifier: Environment :: Console
Classifier: Intended Audience :: Developers
Classifier: Intended Audience :: Information Technology
Classifier: Intended Audience :: System Administrators
Classifier: License :: OSI Approved :: GNU General Public License v3 or later (GPLv3+)
Classifier: Natural Language :: English
Classifier: Operating System :: POSIX
Classifier: Programming Language :: Python :: 3.5
Classifier: Programming Language :: Python :: 3.6
Classifier: Topic :: System :: Installation/Setup
Classifier: Topic :: System :: Systems Administration
Classifier: Topic :: Utilities
Requires-Python: >=3.5
Requires-Dist: Fabric3 (>=1.14.post1)
Requires-Dist: Click (>=6.7)
Requires-Dist: click-help-colors (>=0.4)
Requires-Dist: requests (>=2.18.4)
